reldi/__init__.py
reldi/auth.py
reldi/client.py
reldi/connection.py
reldi/exceptions.py
reldi/lemmatiser.py
reldi/lexicon.py
reldi/ner_tagger.py
reldi/parser.py
reldi/restorer.py
reldi/tagger.py
reldi-1.7.dist-info/DESCRIPTION.rst
reldi-1.7.dist-info/METADATA
reldi-1.7.dist-info/RECORD
reldi-1.7.dist-info/WHEEL
reldi-1.7.dist-info/metadata.json
reldi-1.7.dist-info/top_level.txt
