Metadata-Version: 2.0
Name: reldi
Version: 1.7
Summary: Python library for the ReLDI API
Home-page: https://github.com/clarinsi/reldi-lib
Author: Filip Petkovski
Author-email: filip.petkovsky@gmail.com
License: Apache License 2.0
Keywords: reldi,linguistics
Platform: UNKNOWN
